MANIFEST.in
setup.py
ppp_questionparsing_ml_standalone/__init__.py
ppp_questionparsing_ml_standalone/__main__.py
ppp_questionparsing_ml_standalone/config.py
ppp_questionparsing_ml_standalone/dataset.py
ppp_questionparsing_ml_standalone/dataset_generation.py
ppp_questionparsing_ml_standalone/learn.py
ppp_questionparsing_ml_standalone/linear_classifier.py
ppp_questionparsing_ml_standalone/preprocessing.py
ppp_questionparsing_ml_standalone/requesthandler.py
ppp_questionparsing_ml_standalone/triple_extractor.py
ppp_questionparsing_ml_standalone/utils.py
ppp_questionparsing_ml_standalone.egg-info/PKG-INFO
ppp_questionparsing_ml_standalone.egg-info/SOURCES.txt
ppp_questionparsing_ml_standalone.egg-info/dependency_links.txt
ppp_questionparsing_ml_standalone.egg-info/requires.txt
ppp_questionparsing_ml_standalone.egg-info/top_level.txt
ppp_questionparsing_ml_standalone/data/AnnotatedQuestions.txt