Metadata-Version: 1.1
Name: ppp-questionparsing-ml-standalone
Version: 0.4
Summary: Compute triplets from a question, with an ML approach
Home-page: https://github.com/ProjetPP
Author: Quentin Cormier
Author-email: quentin.cormier@ens-lyon.fr
License: MIT
Platform: UNKNOWN
Classifier: Environment :: No Input/Output (Daemon)
Classifier: Development Status :: 1 - Planning
Classifier: Intended Audience :: System Administrators
Classifier: License :: OSI Approved :: MIT License
Classifier: Operating System :: OS Independent
Classifier: Programming Language :: Python :: 3
Classifier: Programming Language :: Python :: 3.2
Classifier: Programming Language :: Python :: 3.3
Classifier: Programming Language :: Python :: 3.4
Classifier: Topic :: Internet :: WWW/HTTP :: WSGI :: Application
Classifier: Topic :: Software Development :: Libraries
